[
    {
        "number": 1,
        "id": "134312412",
        "names": "Angelo",
        "lastname": "asdfasdf",
        "email": "angelo05@gmail.com",
        "adress": "asgdgs",
        "phone": "3123213139",
        "borndate": "2024-04-11",
        "password": "Celeste93",
        "status": "activo",
        "rol": "Usuario",
        "creationDate": "2024-04-15T18:43:03.829Z"
    },
    {
        "number": 2,
        "id": "1232597687",
        "names": "Angelo",
        "lastname": "Moron",
        "email": "angelofabianmoron05@gmail.com",
        "adress": "Colombia",
        "phone": "3113784301",
        "borndate": "2005-06-11",
        "password": "Lockina05",
        "status": "activo",
        "rol": "Usuario",
        "creationDate": "2024-04-15T18:46:14.795Z"
    },
    {
        "number": 3,
        "id": "12324234",
        "names": "Juan",
        "lastname": "Ramirez",
        "email": "Jinjin@gmail.com",
        "adress": "asgdgs",
        "phone": "654161965465",
        "borndate": "2024-04-14",
        "password": "lOCKINA05",
        "status": "activo",
        "rol": "Usuario",
        "creationDate": "2024-04-15T19:50:44.419Z"
    },
    {
        "number": 4,
        "id": "2121212120",
        "names": "Elba",
        "lastname": "Guevara",
        "email": "elba@gmail.com",
        "adress": "Venezuela",
        "phone": "3100000000",
        "borndate": "2007-08-10",
        "password": "Lockina05",
        "status": "activo",
        "rol": "Usuario",
        "creationDate": "2024-04-15T21:21:12.615Z"
    },
    {
        "number": 5,
        "id": "1089096866",
        "names": "Juan",
        "lastname": "Osorio",
        "email": "esteban@mail.com",
        "adress": "Cuba",
        "phone": "3177304288",
        "borndate": "2004-10-14",
        "password": "Mamaguevo01",
        "status": "activo",
        "rol": "Usuario",
        "creationDate": "2024-04-22T18:30:57.263Z"
    },
    {
        "number": 6,
        "id": "1234567",
        "names": "Instructor",
        "lastname": "Jorge",
        "email": "angelo05234@gmail.com",
        "adress": "Colombia",
        "phone": "31133123213",
        "borndate": "2024-04-09",
        "password": "HolaMundo1234",
        "status": "activo",
        "rol": "Usuario",
        "creationDate": "2024-04-22T19:13:05.926Z"
    },
    {
        "number": 7,
        "id": "13241324",
        "names": "Angelo",
        "lastname": "asdfasdf",
        "email": "angeldsfao05@gmail.com",
        "adress": "ASDasd",
        "phone": "132423142341",
        "borndate": "2024-04-25",
        "password": "Hola12345",
        "status": "activo",
        "rol": "Usuario",
        "creationDate": "2024-04-22T19:15:53.184Z"
    },
    {
        "number": 8,
        "id": "1324123443",
        "names": "Angelo",
        "lastname": "asdfasdf",
        "email": "dfg@sfd.hj",
        "adress": "Colombia",
        "phone": "213131231231",
        "borndate": "2024-04-10",
        "password": "Hola12345",
        "status": "activo",
        "rol": "Usuario",
        "creationDate": "2024-04-22T19:19:22.799Z"
    },
    {
        "number": 9,
        "id": "132413240",
        "names": "dfasadsf",
        "lastname": "adsfadfs",
        "email": "aasdffdasngelo05@gmail.com",
        "adress": "Colombia",
        "phone": "34312343124",
        "borndate": "2005-02-15",
        "password": "HolaMundo1234",
        "status": "activo",
        "rol": "Usuario",
        "creationDate": "2024-04-29T19:33:36.038Z"
    },
    {
        "number": 10,
        "id": "1234568979",
        "names": "Horacio",
        "lastname": "Gomez",
        "email": "oracio@gmail.com",
        "adress": "Dosquebradas Calle 8 me perdi",
        "phone": "1324564789",
        "borndate": "2007-06-28",
        "password": "Contraseña12",
        "status": "activo",
        "rol": "Usuario",
        "creationDate": "2024-04-30T21:28:42.914Z"
    }
]